abageotests/__init__.py
abageotests/ababase/AbaqusContact.py
abageotests/ababase/AbaqusGeometry.py
abageotests/ababase/AbaqusLoad.py
abageotests/ababase/AbaqusMaterial.py
abageotests/ababase/AbaqusMesh.py
abageotests/ababase/AbaqusModelBase.py
abageotests/ababase/AbaqusOutput.py
abageotests/ababase/AbaqusStep.py
abageotests/ababase/AbaqusSubroutine.py
abageotests/ababase/AbaqusVariable.py
abageotests/ababase/__init__.py
abageotests/ababase/abaqusConstants.py
abageotests/abadst/AbaqusDirectShearTest.py
abageotests/abadst/__init__.py
abageotests/abadst/dst.py
abageotests/abadst/dst_output_fric.py
abageotests/abadst/dst_output_vfric.py
abageotests/abageoabstract/AbaGeoTestBase.py
abageotests/abageoabstract/__init__.py
abageotests/abapilepenetrating/AbaqusPilePenetrating.py
abageotests/abapilepenetrating/__init__.py
abageotests/abapullout/AbaqusPullOut.py
abageotests/abapullout/__init__.py
abageotests/abapullout/pullout.py
abageotests-0.0.5.dist-info/LICENSE.txt
abageotests-0.0.5.dist-info/METADATA
abageotests-0.0.5.dist-info/WHEEL
abageotests-0.0.5.dist-info/top_level.txt
abageotests-0.0.5.dist-info/RECORD
