Metadata-Version: 2.1
Name: abageotests
Version: 0.0.5
Summary: A package to generate and execute python scripts of abaqus models of geotechnical tests
Home-page: https://github.com/Hailin-Wang/abageotests
Author: WANG Hailin
Author-email: hailin.wang@connect.polyu.hk
License: UNKNOWN
Platform: UNKNOWN
Classifier: Programming Language :: Python :: 3
Classifier: License :: OSI Approved :: MIT License
Classifier: Operating System :: OS Independent
Requires-Python: >=3.6
License-File: LICENSE.txt
